StringC.py
conf.py
StringC-1.0.1.dist-info/LICENSE.txt
StringC-1.0.1.dist-info/METADATA
StringC-1.0.1.dist-info/WHEEL
StringC-1.0.1.dist-info/top_level.txt
StringC-1.0.1.dist-info/RECORD
