Metadata-Version: 2.1
Name: StringC
Version: 1.0.1
Summary: This Package Convert numeric date in the string to the datetime object
Home-page: https://bitbucket.org/mvahid/stringc.git
Author: Mohammad Vahid
Author-email: m.vahid.da@gmail.com
License: UNKNOWN
Platform: UNKNOWN
Classifier: Programming Language :: Python :: 3
Classifier: Programming Language :: Python :: 3.6
Classifier: Programming Language :: Python :: 3.7
Classifier: Programming Language :: Python :: 3.8
Classifier: License :: OSI Approved :: MIT License
Classifier: Operating System :: OS Independent
Classifier: Natural Language :: Persian
Classifier: Topic :: Software Development :: Libraries :: Python Modules
Classifier: Topic :: Text Processing
Classifier: Topic :: Text Editors :: Text Processing
Requires-Dist: persiantools (~=2.1.1)
Requires-Dist: python-dateutil (~=2.8.1)
Requires-Dist: regex (~=2021.3.17)
Requires-Dist: Unidecode (~=1.2.0)
Provides-Extra: dev
Requires-Dist: pytest (>=3.7) ; extra == 'dev'
Requires-Dist: twine (>=3.4.1) ; extra == 'dev'
Requires-Dist: check-manifest (>=0.46) ; extra == 'dev'
